cs/pop3.py
cs.pop3-20240316.dist-info/METADATA
cs.pop3-20240316.dist-info/WHEEL
cs.pop3-20240316.dist-info/entry_points.txt
cs.pop3-20240316.dist-info/top_level.txt
cs.pop3-20240316.dist-info/RECORD
