Metadata-Version: 2.1
Name: cs.pop3
Version: 20240316
Summary: POP3 stuff, particularly a streaming downloader and a simple command line which runs it.
Author-email: Cameron Simpson <cs@cskk.id.au>
License: GNU General Public License v3 or later (GPLv3+)
Project-URL: URL, https://bitbucket.org/cameron_simpson/css/commits/all
Keywords: python3
Platform: UNKNOWN
Classifier: Programming Language :: Python
Classifier: Programming Language :: Python :: 3
Classifier: Environment :: Console
Classifier: Topic :: Communications :: Email :: Post-Office :: POP3
Classifier: Topic :: Internet
Classifier: Topic :: Utilities
Classifier: Development Status :: 4 - Beta
Classifier: Intended Audience :: Developers
Classifier: Operating System :: OS Independent
Classifier: License :: OSI Approved :: GNU General Public License v3 or later (GPLv3+)
Requires-Dist: cs.cmdutils >=20210407.1
Requires-Dist: cs.fs >=20240316
Requires-Dist: cs.lex >=20240211
Requires-Dist: cs.logutils >=20230212
Requires-Dist: cs.pfx >=20230604
Requires-Dist: cs.queues >=20240305
Requires-Dist: cs.resources >=20240316
Requires-Dist: cs.result >=20210407
Requires-Dist: cs.threads >=20240303
Requires-Dist: cs.upd >=20240216
